fastapi_pundra/__init__.py
fastapi_pundra/common/__init__.py
fastapi_pundra/common/helpers.py
fastapi_pundra/common/jwt_utils.py
fastapi_pundra/common/password.py
fastapi_pundra/common/mailer/__init__.py
fastapi_pundra/common/mailer/inline_css.py
fastapi_pundra/common/mailer/mail.py
fastapi_pundra/common/mailer/mail_queue.py
fastapi_pundra/common/mailer/mail_templating.py
fastapi_pundra/common/mailer/task.py
fastapi_pundra/common/raw_sql/__init__.py
fastapi_pundra/common/raw_sql/utils.py
fastapi_pundra/common/scheduler/__init__.py
fastapi_pundra/common/scheduler/celery.py
fastapi_pundra/common/scheduler/schedule.py
fastapi_pundra/common/scheduler/schedule_cron.py
fastapi_pundra/gql_berry/__init__.py
fastapi_pundra/gql_berry/common_gql_type.py
fastapi_pundra/gql_berry/exception.py
fastapi_pundra/gql_berry/pagination.py
fastapi_pundra/gql_berry/pydantic_experimental.py
fastapi_pundra/gql_berry/strawberry_resolver_utils.py
fastapi_pundra/gql_berry/validation.py
fastapi_pundra/rest/__init__.py
fastapi_pundra/rest/exceptions.py
fastapi_pundra/rest/global_exception_handler.py
fastapi_pundra/rest/helpers.py
fastapi_pundra/rest/openapi.py
fastapi_pundra/rest/paginate.py
fastapi_pundra/rest/validation.py
fastapi_pundra-0.0.20.dist-info/METADATA
fastapi_pundra-0.0.20.dist-info/WHEEL
fastapi_pundra-0.0.20.dist-info/licenses/LICENSE
fastapi_pundra-0.0.20.dist-info/RECORD
