Metadata-Version: 2.4
Name: fastapi-pundra
Version: 0.0.20
Summary: Pundra: Your FastAPI Companion for Productivity
Project-URL: Homepage, https://github.com/code4mk/fastapi-pundra
Project-URL: Source, https://github.com/code4mk/fastapi-pundra
Project-URL: Changelog, https://github.com/code4mk/fastapi-pundra/blob/main/CHANGELOG.md
Project-URL: Documentation, https://github.com/code4mk/fastapi-pundra
Project-URL: Bug Tracker, https://github.com/code4mk/fastapi-pundra/issues
Author-email: Mostafa Kamal <hiremostafa@gmail.com>
License-Expression: MIT
License-File: LICENSE
Keywords: code4mk,fastapi,graphql,pundra,python,rest_api,strawberry
Classifier: Development Status :: 3 - Alpha
Classifier: Framework :: FastAPI
Classifier: Intended Audience :: Developers
Classifier: License :: OSI Approved :: MIT License
Classifier: Operating System :: OS Independent
Classifier: Programming Language :: Python :: 3.10
Classifier: Programming Language :: Python :: 3.11
Classifier: Programming Language :: Python :: 3.12
Requires-Python: >=3.10
Requires-Dist: bcrypt
Requires-Dist: python-dotenv
Requires-Dist: python-jose
Requires-Dist: requests
Provides-Extra: dev
Requires-Dist: black>=23.0.0; extra == 'dev'
Requires-Dist: mypy>=1.0.0; extra == 'dev'
Requires-Dist: pytest-asyncio>=0.21.0; extra == 'dev'
Requires-Dist: pytest>=7.0.0; extra == 'dev'
Requires-Dist: ruff>=0.0.270; extra == 'dev'
